ai/__init__.py
ippr/__init__.py
mwa/__init__.py
aireq-0.5.dist-info/METADATA
aireq-0.5.dist-info/WHEEL
aireq-0.5.dist-info/top_level.txt
aireq-0.5.dist-info/RECORD
