Metadata-Version: 2.1
Name: aireq
Version: 0.5
Summary: It contains all ipppr codes
Author: Shashank
